setup.cfg
setup.py
missing_values_kamakshi/__init__.py
missing_values_kamakshi/basic.py
missing_values_kamakshi/datahandler.py
missing_values_kamakshi.egg-info/PKG-INFO
missing_values_kamakshi.egg-info/SOURCES.txt
missing_values_kamakshi.egg-info/dependency_links.txt
missing_values_kamakshi.egg-info/top_level.txt