Metadata-Version: 1.2
Name: missing-values-kamakshi
Version: 0.0.1
Summary: This is a package for handling missing values in a given dataset.
Home-page: https://github.com/kamakshibehl/missing_values_kamakshi.git
Author: kamakshi/kamakshi_behl
Author-email: kamakshi.behl22@gmail.com
License: UNKNOWN
Download-URL: https://github.com/kamakshibehl/missing_values_kamakshi/archive/1.0.0.tar.gz
Platform: UNKNOWN
Classifier: Programming Language :: Python :: 3
Classifier: License :: OSI Approved :: MIT License
Classifier: Operating System :: OS Independent
Requires-Python: >=3.6
